limitly/__init__.py
limitly/cli.py
limitly/client.py
limitly/types.py
limitly/version.py
limitly/modules/__init__.py
limitly/modules/api_keys.py
limitly/modules/plans.py
limitly/modules/users.py
limitly/modules/validation.py
limitly_python-1.0.3.dist-info/licenses/LICENSE
limitly_python-1.0.3.dist-info/METADATA
limitly_python-1.0.3.dist-info/WHEEL
limitly_python-1.0.3.dist-info/entry_points.txt
limitly_python-1.0.3.dist-info/top_level.txt
limitly_python-1.0.3.dist-info/RECORD
