Metadata-Version: 2.4
Name: limitly-python
Version: 1.0.3
Summary: Official Python SDK for Limitly - API Key management, plans, users and request validation
Author-email: Limitly Team <hi@limitly.dev>
Maintainer-email: Limitly Team <hi@limitly.dev>
License: MIT
Project-URL: Homepage, https://github.com/limitlydev/limitly-python
Project-URL: Documentation, https://docs.limitly.com
Project-URL: Repository, https://github.com/limitlydev/limitly-python
Project-URL: Bug Tracker, https://github.com/limitlydev/limitly-python/issues
Keywords: limitly,api,rate-limiting,api-keys,sdk,python
Classifier: Development Status :: 4 - Beta
Classifier: Intended Audience :: Developers
Classifier: License :: OSI Approved :: MIT License
Classifier: Operating System :: OS Independent
Classifier: Programming Language :: Python :: 3
Classifier: Programming Language :: Python :: 3.8
Classifier: Programming Language :: Python :: 3.9
Classifier: Programming Language :: Python :: 3.10
Classifier: Programming Language :: Python :: 3.11
Classifier: Programming Language :: Python :: 3.12
Classifier: Topic :: Software Development :: Libraries :: Python Modules
Classifier: Topic :: Internet :: WWW/HTTP :: HTTP Servers
Classifier: Topic :: System :: Networking :: Monitoring
Requires-Python: >=3.8
License-File: LICENSE
Requires-Dist: requests>=2.25.0
Requires-Dist: typing-extensions>=4.0.0; python_version < "3.8"
Provides-Extra: dev
Requires-Dist: pytest>=7.0.0; extra == "dev"
Requires-Dist: pytest-asyncio>=0.21.0; extra == "dev"
Requires-Dist: pytest-cov>=4.0.0; extra == "dev"
Requires-Dist: black>=23.0.0; extra == "dev"
Requires-Dist: isort>=5.12.0; extra == "dev"
Requires-Dist: flake8>=6.0.0; extra == "dev"
Requires-Dist: mypy>=1.0.0; extra == "dev"
Requires-Dist: types-requests>=2.28.0; extra == "dev"
Dynamic: license-file
